dictionary/__init__.py
dictionary/dictionary.py
furkanakkurt_simpledic-2.0.2.dist-info/METADATA
furkanakkurt_simpledic-2.0.2.dist-info/WHEEL
furkanakkurt_simpledic-2.0.2.dist-info/top_level.txt
furkanakkurt_simpledic-2.0.2.dist-info/RECORD
