Metadata-Version: 2.1
Name: furkanakkurt-simpledic
Version: 2.0.2
Summary: UNKNOWN
Author: Furkan Akkurt
License: UNKNOWN
Platform: UNKNOWN
Requires-Python: >=3.8
Requires-Dist: requests (>=2.23.0)
